PySortedSet/PySortedSet.py
PySortedSet/PySortedSet_tests.py
PySortedSet/PySortedSet_versus_set.py
PySortedSet-1.2.dist-info/LICENSE
PySortedSet-1.2.dist-info/METADATA
PySortedSet-1.2.dist-info/WHEEL
PySortedSet-1.2.dist-info/entry_points.txt
PySortedSet-1.2.dist-info/top_level.txt
PySortedSet-1.2.dist-info/RECORD
