Metadata-Version: 2.1
Name: PySortedSet
Version: 1.2
Summary: This package contains implementation of the library "PySortedSet". PySortedSet is a data type supporting a sorted set which is aware of indices.
Home-page: https://github.com/DigitalCreativeApkDev/PySortedSet
Author: DigitalCreativeApkDev
Author-email: digitalcreativeapkdev2022@gmail.com
License: MIT
Platform: UNKNOWN
Classifier: Programming Language :: Python :: 3
Classifier: Programming Language :: Python :: 3.7
